{
  "annotations": {
    "list": []
  },
  "editable": false,
  "fiscalYearStartMonth": 0,
  "graphTooltip": 1,
  "id": null,
  "links": [],
  "panels": [
    {
      "datasource": {
        "type": "prometheus",
        "uid": "openinfra-prometheus"
      },
      "fieldConfig": {
        "defaults": {
          "unit": "percentunit"
        },
        "overrides": []
      },
      "gridPos": {
        "h": 8,
        "w": 8,
        "x": 0,
        "y": 0
      },
      "id": 1,
      "options": {
        "legend": {
          "displayMode": "table",
          "placement": "bottom"
        },
        "tooltip": {
          "mode": "multi"
        }
      },
      "targets": [
        {
          "expr": "up{job=\"openinfra-multisite\",region=~\"$region\",site=~\"$site\"}",
          "legendFormat": "{{region}} / {{site}}",
          "refId": "A"
        }
      ],
      "title": "Site API availability",
      "type": "timeseries"
    },
    {
      "datasource": {
        "type": "prometheus",
        "uid": "openinfra-prometheus"
      },
      "fieldConfig": {
        "defaults": {
          "unit": "s"
        },
        "overrides": []
      },
      "gridPos": {
        "h": 8,
        "w": 8,
        "x": 8,
        "y": 0
      },
      "id": 2,
      "options": {
        "legend": {
          "displayMode": "table",
          "placement": "bottom"
        },
        "tooltip": {
          "mode": "multi"
        }
      },
      "targets": [
        {
          "expr": "histogram_quantile(0.95, sum by (le, region, site) (rate(openinfra_http_request_duration_seconds_bucket{job=\"openinfra-multisite\",service=\"openinfra-api\",region=~\"$region\",site=~\"$site\"}[5m])))",
          "legendFormat": "{{region}} / {{site}}",
          "refId": "A"
        }
      ],
      "title": "API p95 latency by site",
      "type": "timeseries"
    },
    {
      "datasource": {
        "type": "prometheus",
        "uid": "openinfra-prometheus"
      },
      "fieldConfig": {
        "defaults": {
          "unit": "percentunit"
        },
        "overrides": []
      },
      "gridPos": {
        "h": 8,
        "w": 8,
        "x": 16,
        "y": 0
      },
      "id": 3,
      "options": {
        "legend": {
          "displayMode": "table",
          "placement": "bottom"
        },
        "tooltip": {
          "mode": "multi"
        }
      },
      "targets": [
        {
          "expr": "sum by (region, site) (rate(openinfra_http_requests_total{job=\"openinfra-multisite\",status_class=\"5xx\",region=~\"$region\",site=~\"$site\"}[5m])) / clamp_min(sum by (region, site) (rate(openinfra_http_requests_total{job=\"openinfra-multisite\",region=~\"$region\",site=~\"$site\"}[5m])), 0.001)",
          "legendFormat": "{{region}} / {{site}}",
          "refId": "A"
        }
      ],
      "title": "HTTP 5xx ratio by site",
      "type": "timeseries"
    },
    {
      "datasource": {
        "type": "prometheus",
        "uid": "openinfra-prometheus"
      },
      "fieldConfig": {
        "defaults": {
          "unit": "s"
        },
        "overrides": []
      },
      "gridPos": {
        "h": 8,
        "w": 12,
        "x": 0,
        "y": 8
      },
      "id": 4,
      "options": {
        "legend": {
          "displayMode": "table",
          "placement": "bottom"
        },
        "tooltip": {
          "mode": "multi"
        }
      },
      "targets": [
        {
          "expr": "max by (region, site) (openinfra_multisite_agent_lag_seconds{region=~\"$region\",site=~\"$site\"})",
          "legendFormat": "{{region}} / {{site}}",
          "refId": "A"
        }
      ],
      "title": "Discovery agent heartbeat lag",
      "type": "timeseries"
    },
    {
      "datasource": {
        "type": "prometheus",
        "uid": "openinfra-prometheus"
      },
      "fieldConfig": {
        "defaults": {
          "unit": "percentunit"
        },
        "overrides": []
      },
      "gridPos": {
        "h": 8,
        "w": 12,
        "x": 12,
        "y": 8
      },
      "id": 5,
      "options": {
        "legend": {
          "displayMode": "table",
          "placement": "bottom"
        },
        "tooltip": {
          "mode": "multi"
        }
      },
      "targets": [
        {
          "expr": "min by (region, site) (openinfra_multisite_agent_health{region=~\"$region\",site=~\"$site\"})",
          "legendFormat": "{{region}} / {{site}}",
          "refId": "A"
        }
      ],
      "title": "Discovery agent health",
      "type": "timeseries"
    },
    {
      "datasource": {
        "type": "prometheus",
        "uid": "openinfra-prometheus"
      },
      "fieldConfig": {
        "defaults": {
          "unit": "s"
        },
        "overrides": []
      },
      "gridPos": {
        "h": 8,
        "w": 12,
        "x": 0,
        "y": 16
      },
      "id": 6,
      "options": {
        "legend": {
          "displayMode": "table",
          "placement": "bottom"
        },
        "tooltip": {
          "mode": "multi"
        }
      },
      "targets": [
        {
          "expr": "max by (region, site) (openinfra_db_replica_lag_seconds{job=\"openinfra-multisite\",region=~\"$region\",site=~\"$site\"})",
          "legendFormat": "{{region}} / {{site}}",
          "refId": "A"
        }
      ],
      "title": "PostgreSQL replica lag by site",
      "type": "timeseries"
    },
    {
      "datasource": {
        "type": "prometheus",
        "uid": "openinfra-prometheus"
      },
      "fieldConfig": {
        "defaults": {
          "unit": "s"
        },
        "overrides": []
      },
      "gridPos": {
        "h": 8,
        "w": 12,
        "x": 12,
        "y": 16
      },
      "id": 7,
      "options": {
        "legend": {
          "displayMode": "table",
          "placement": "bottom"
        },
        "tooltip": {
          "mode": "multi"
        }
      },
      "targets": [
        {
          "expr": "max by (region, site) (openinfra_async_oldest_ready_age_seconds{job=\"openinfra-multisite\",kind=\"jobs\",region=~\"$region\",site=~\"$site\"})",
          "legendFormat": "{{region}} / {{site}}",
          "refId": "A"
        }
      ],
      "title": "Oldest ready job by site",
      "type": "timeseries"
    },
    {
      "datasource": {
        "type": "prometheus",
        "uid": "openinfra-prometheus"
      },
      "fieldConfig": {
        "defaults": {},
        "overrides": []
      },
      "gridPos": {
        "h": 8,
        "w": 24,
        "x": 0,
        "y": 24
      },
      "id": 8,
      "options": {
        "legend": {
          "displayMode": "table",
          "placement": "bottom"
        },
        "tooltip": {
          "mode": "multi"
        }
      },
      "targets": [
        {
          "expr": "sum by (region, site, status) (openinfra_async_queue_depth{job=\"openinfra-multisite\",kind=\"jobs\",region=~\"$region\",site=~\"$site\"})",
          "legendFormat": "{{region}} / {{site}} / {{status}}",
          "refId": "A"
        }
      ],
      "title": "Queue depth by site",
      "type": "timeseries"
    }
  ],
  "refresh": "30s",
  "schemaVersion": 41,
  "tags": [
    "openinfra",
    "multisite",
    "sre",
    "p17"
  ],
  "templating": {
    "list": [
      {
        "name": "region",
        "label": "Region",
        "type": "query",
        "datasource": {
          "type": "prometheus",
          "uid": "openinfra-prometheus"
        },
        "query": {
          "query": "label_values(up{job=\"openinfra-multisite\"}, region)",
          "refId": "PrometheusVariableQueryEditor-VariableQuery"
        },
        "includeAll": true,
        "allValue": ".*",
        "multi": true,
        "refresh": 1,
        "sort": 1
      },
      {
        "name": "site",
        "label": "Site",
        "type": "query",
        "datasource": {
          "type": "prometheus",
          "uid": "openinfra-prometheus"
        },
        "query": {
          "query": "label_values(up{job=\"openinfra-multisite\",region=~\"$region\"}, site)",
          "refId": "PrometheusVariableQueryEditor-VariableQuery"
        },
        "includeAll": true,
        "allValue": ".*",
        "multi": true,
        "refresh": 1,
        "sort": 1
      }
    ]
  },
  "time": {
    "from": "now-6h",
    "to": "now"
  },
  "timezone": "browser",
  "title": "OpenInfra Multisite Operations",
  "uid": "openinfra-multisite-operations",
  "version": 1
}
